BonusLab/__init__.py
BonusLab/dataset_loader.py
BonusLab/init_grader_.py
BonusLab/data/btc.csv
BonusLab/data/eth.csv
BonusLab/data/spreads.csv
BonusLab/data/triple_vertical.csv
BonusLab/tests/q1_1.py
BonusLab/tests/q1_2.py
BonusLab/tests/q1_5.py
BonusLab/tests/q1_6.py
BonusLab/tests/q1_7.py
BonusLab/tests/q2_2.py
BonusLab/tests/q2_3.py
BonusLab/tests/q3_1.py
BonusLab/tests/q3_2.py
BonusLab/tests/q3_3.py
BonusLab/tests/q3_5.py
BonusLab/tests/q3_6.py
BonusLab/tests/q3_7.py
BonusLab/tests/q3_8.py
febedatasetswits/__init__.py
febedatasetswits/dataset_loader.py
febedatasetswits/data/station_origin_center_1_data.csv
lab01/__init__.py
lab01/image_loader.py
lab01/init_grader_.py
lab01/images/cat_lengths.png
lab01/images/gradescope.png
lab01/tests/__init__.py
lab01/tests/q3_1_2.py
lab01/tests/q3_3_1.py
lab01/tests/q3_3_2.py
lab01/tests/q4_1_1.py
lab01/tests/q51.py
lab01/tests/q5_1_1.py
lab02/__init__.py
lab02/dataset_loader.py
lab02/init_grader_.py
lab02/data/imdb.csv
lab02/data/world_population.csv
lab02/tests/q11.py
lab02/tests/q21.py
lab02/tests/q211.py
lab02/tests/q32.py
lab02/tests/q33.py
lab02/tests/q34.py
lab02/tests/q35.py
lab02/tests/q36.py
lab02/tests/q41.py
lab02/tests/q42.py
lab03/__init__.py
lab03/dataset_loader.py
lab03/init_grader_.py
lab03/data/imdb.csv
lab03/data/more_restaurant_bills.csv
lab03/data/world_population.csv
lab03/tests/q11.py
lab03/tests/q111.py
lab03/tests/q121.py
lab03/tests/q131.py
lab03/tests/q211.py
lab03/tests/q212.py
lab03/tests/q213.py
lab03/tests/q221.py
lab03/tests/q231.py
lab03/tests/q31.py
lab03/tests/q32.py
lab03/tests/q41.py
lab03/tests/q42.py
lab03/tests/q43.py
lab03/tests/q511.py
lab03/tests/q521.py
lab03/tests/q522.py
lab03/tests/q523.py
lab03/tests/q524.py
lab04/__init__.py
lab04/dataset_loader.py
lab04/init_grader_.py
lab04/data/movies_by_year.csv
lab04/data/raw_compensation.csv
lab04/tests/q11.py
lab04/tests/q13.py
lab04/tests/q14.py
lab04/tests/q21.py
lab04/tests/q22.py
lab04/tests/q23.py
lab04/tests/q24.py
febedatasets-1.8.dist-info/LICENCE
febedatasets-1.8.dist-info/METADATA
febedatasets-1.8.dist-info/WHEEL
febedatasets-1.8.dist-info/top_level.txt
febedatasets-1.8.dist-info/RECORD
