Metadata-Version: 2.1
Name: febedatasets
Version: 1.8
Summary: A package to load different datasets used in a Wits University First Year engineering datascince course
Home-page: https://github.com/Tech-Gui/febe1004Datasets
Author: Isaiah Chiraira
Author-email: itchiraira@gmail.com
License: MIT
Classifier: Programming Language :: Python :: 3
Classifier: License :: OSI Approved :: MIT License
Classifier: Operating System :: OS Independent
Requires-Python: >=3.6
License-File: LICENCE
Requires-Dist: pandas
Requires-Dist: Pillow
Requires-Dist: otter-grader
